<?xml version="1.0" encoding="UTF-8"?>
<!DOCTYPE mapper PUBLIC "-//mybatis.org//DTD Mapper 3.0//EN" "http://mybatis.org/dtd/mybatis-3-mapper.dtd">
<mapper namespace="com.zhku.meeting.mapper.ShowStatusMapper">
  <resultMap id="BaseResultMap" type="com.zhku.meeting.entities.ShowStatus">
    <!--
      WARNING - @mbg.generated
      This element is automatically generated by MyBatis Generator, do not modify.
      This element was generated on Tue May 20 20:12:15 CST 2025.
    -->
    <id column="room_id" jdbcType="INTEGER" property="roomId" />
    <result column="room_no" jdbcType="VARCHAR" property="roomNo" />
    <result column="one" jdbcType="BIT" property="one" />
    <result column="two" jdbcType="BIT" property="two" />
    <result column="three" jdbcType="BIT" property="three" />
    <result column="four" jdbcType="BIT" property="four" />
    <result column="five" jdbcType="BIT" property="five" />
    <result column="room_size" jdbcType="INTEGER" property="roomSize" />
    <result column="air" jdbcType="BIT" property="air" />
    <result column="projector" jdbcType="BIT" property="projector" />
  </resultMap>
  <delete id="deleteByPrimaryKey" parameterType="java.lang.Integer">
    <!--
      WARNING - @mbg.generated
      This element is automatically generated by MyBatis Generator, do not modify.
      This element was generated on Tue May 20 20:12:15 CST 2025.
    -->
    delete from status
    where room_id = #{roomId,jdbcType=INTEGER}
  </delete>
  <insert id="insert" parameterType="com.zhku.meeting.entities.ShowStatus">
    <!--
      WARNING - @mbg.generated
      This element is automatically generated by MyBatis Generator, do not modify.
      This element was generated on Tue May 20 20:12:15 CST 2025.
    -->
    insert into status (room_id, room_no, one, 
      two, three, four, five, 
      room_size, air, projector)
    values (#{roomId,jdbcType=INTEGER}, #{roomNo,jdbcType=VARCHAR}, #{one,jdbcType=BIT}, 
      #{two,jdbcType=BIT}, #{three,jdbcType=BIT}, #{four,jdbcType=BIT}, #{five,jdbcType=BIT}, 
      #{roomSize,jdbcType=INTEGER}, #{air,jdbcType=BIT}, #{projector,jdbcType=BIT})
  </insert>
  <update id="updateByPrimaryKey" parameterType="com.zhku.meeting.entities.ShowStatus">
    <!--
      WARNING - @mbg.generated
      This element is automatically generated by MyBatis Generator, do not modify.
      This element was generated on Tue May 20 20:12:15 CST 2025.
    -->
    update status
    set room_no = #{roomNo,jdbcType=VARCHAR},
      one = #{one,jdbcType=BIT},
      two = #{two,jdbcType=BIT},
      three = #{three,jdbcType=BIT},
      four = #{four,jdbcType=BIT},
      five = #{five,jdbcType=BIT},
      room_size = #{roomSize,jdbcType=INTEGER},
      air = #{air,jdbcType=BIT},
      projector = #{projector,jdbcType=BIT}
    where room_id = #{roomId,jdbcType=INTEGER}
  </update>
  <select id="selectByPrimaryKey" parameterType="java.lang.Integer" resultMap="BaseResultMap">
    <!--
      WARNING - @mbg.generated
      This element is automatically generated by MyBatis Generator, do not modify.
      This element was generated on Tue May 20 20:12:15 CST 2025.
    -->
    select room_id, room_no, one, two, three, four, five, room_size, air, projector
    from status
    where room_id = #{roomId,jdbcType=INTEGER}
  </select>
  <select id="selectAll" resultMap="BaseResultMap">
    <!--
      WARNING - @mbg.generated
      This element is automatically generated by MyBatis Generator, do not modify.
      This element was generated on Tue May 20 20:12:15 CST 2025.
    -->
    select room_id, room_no, one, two, three, four, five, room_size, air, projector
    from status
  </select>
</mapper>